[
  {
    "condition": {
      "typeReachable": "org.mockito.internal.debugging.Java9PlusLocationImpl$MetadataShim"
    },
    "name": "java.lang.Object",
    "methods": [
      {
        "name": "toString",
        "parameterTypes": []
      }
    ]
  },
  {
    "condition": {
      "typeReachable": "org.mockito.internal.debugging.Java9PlusLocationImpl"
    },
    "name": "java.lang.StackWalker",
    "methods": [
      {
        "name": "getInstance",
        "parameterTypes": [
          "java.util.Set",
          "int"
        ]
      },
      {
        "name": "walk",
        "parameterTypes": [
          "java.util.function.Function"
        ]
      }
    ]
  },
  {
    "condition": {
      "typeReachable": "org.mockito.internal.debugging.LocationFactory"
    },
    "name": "java.lang.StackWalker"
  },
  {
    "condition": {
      "typeReachable": "org.mockito.internal.debugging.Java9PlusLocationImpl"
    },
    "name": "java.lang.StackWalker$Option"
  },
  {
    "condition": {
      "typeReachable": "org.mockito.internal.debugging.Java9PlusLocationImpl"
    },
    "name": "java.lang.StackWalker$StackFrame"
  },
  {
    "condition": {
      "typeReachable": "org.mockito.internal.debugging.Java9PlusLocationImpl$MetadataShim"
    },
    "name": "java.lang.StackWalker$StackFrame",
    "methods": [
      {
        "name": "getClassName",
        "parameterTypes": []
      },
      {
        "name": "getFileName",
        "parameterTypes": []
      },
      {
        "name": "getLineNumber",
        "parameterTypes": []
      },
      {
        "name": "getMethodName",
        "parameterTypes": []
      }
    ]
  },
  {
    "condition": {
      "typeReachable": "org.mockito.internal.creation.proxy.InvokeDefaultProxy"
    },
    "name": "java.lang.reflect.InvocationHandler",
    "methods": [
      {
        "name": "invokeDefault",
        "parameterTypes": [
          "java.lang.Object",
          "java.lang.reflect.Method",
          "java.lang.Object[]"
        ]
      }
    ]
  },
  {
    "condition": {
      "typeReachable": "org.mockito.internal.util.KotlinInlineClassUtil"
    },
    "name": "kotlin.jvm.JvmInline"
  },
  {
    "condition": {
      "typeReachable": "org.mockito.internal.configuration.ClassPathLoader"
    },
    "name": "org.mockito.configuration.MockitoConfiguration"
  },
  {
    "condition": {
      "typeReachable": "org.mockito.internal.configuration.plugins.DefaultMockitoPlugins"
    },
    "name": "org.mockito.internal.configuration.DefaultDoNotMockEnforcer",
    "methods": [
      {
        "name": "<init>",
        "parameterTypes": []
      }
    ]
  },
  {
    "condition": {
      "typeReachable": "org.mockito.internal.configuration.plugins.DefaultMockitoPlugins"
    },
    "name": "org.mockito.internal.configuration.InjectingAnnotationEngine",
    "methods": [
      {
        "name": "<init>",
        "parameterTypes": []
      }
    ]
  },
  {
    "condition": {
      "typeReachable": "org.mockito.internal.configuration.plugins.DefaultMockitoPlugins"
    },
    "name": "org.mockito.internal.configuration.plugins.DefaultPluginSwitch",
    "methods": [
      {
        "name": "<init>",
        "parameterTypes": []
      }
    ]
  },
  {
    "condition": {
      "typeReachable": "org.mockito.internal.configuration.plugins.DefaultMockitoPlugins"
    },
    "name": "org.mockito.internal.creation.instance.DefaultInstantiatorProvider",
    "methods": [
      {
        "name": "<init>",
        "parameterTypes": []
      }
    ]
  },
  {
    "condition": {
      "typeReachable": "org.mockito.internal.configuration.plugins.PluginInitializer"
    },
    "name": "org.mockito.internal.creation.proxy.ProxyMockMaker",
    "methods": [
      {
        "name": "<init>",
        "parameterTypes": []
      }
    ]
  },
  {
    "condition": {
      "typeReachable": "org.mockito.internal.configuration.plugins.DefaultMockitoPlugins"
    },
    "name": "org.mockito.internal.exceptions.stacktrace.DefaultStackTraceCleanerProvider",
    "methods": [
      {
        "name": "<init>",
        "parameterTypes": []
      }
    ]
  },
  {
    "condition": {
      "typeReachable": "org.mockito.internal.configuration.plugins.DefaultMockitoPlugins"
    },
    "name": "org.mockito.internal.util.ConsoleMockitoLogger",
    "methods": [
      {
        "name": "<init>",
        "parameterTypes": []
      }
    ]
  },
  {
    "condition": {
      "typeReachable": "org.mockito.internal.configuration.plugins.DefaultMockitoPlugins"
    },
    "name": "org.mockito.internal.util.reflection.ReflectionMemberAccessor",
    "methods": [
      {
        "name": "<init>",
        "parameterTypes": []
      }
    ]
  }
]
